{
  "manojmanoharan007@gmail.com": {
    "_id": "13a18633-ab01-47b0-a571-fe490a9ee2dd",
    "name": "manoj kumar",
    "email": "manojmanoharan007@gmail.com",
    "password": "b'$2b$12$ftQ8TT26Wu2u5cT2ZO/8cOpuLN/QmCDaV7G83F1b5chT020w3ulwm'",
    "phone": "8925153050",
    "state": "Tamil Nadu",
    "district": "Karur",
    "created_at": "2026-01-23T05:46:41.836067",
    "saved_crops": [],
    "saved_fertilizers": [],
    "disease_history": [],
    "last_notification_read_at": "2026-01-23T11:20:15.339850"
  }
}